README.rst
setup.py
vim_bridge/__init__.py
vim_bridge/registry.py
vim_bridge.egg-info/PKG-INFO
vim_bridge.egg-info/SOURCES.txt
vim_bridge.egg-info/dependency_links.txt
vim_bridge.egg-info/not-zip-safe
vim_bridge.egg-info/top_level.txt