Metadata-Version: 1.1
Name: vim-bridge
Version: 0.5
Summary: A Python-to-Vim bridge decorator that allows transparent calls to Python functions in native Vim scripts.
Home-page: http://github.com/nvie/vim_bridge
Author: Vincent Driessen
Author-email: vincent@datafox.nl
License: BSD
Platform: any
Classifier: Development Status :: 4 - Beta
Classifier: Operating System :: OS Independent
Classifier: Programming Language :: Python
Classifier: Programming Language :: Python :: 2.4
Classifier: Programming Language :: Python :: 2.5
Classifier: Programming Language :: Python :: 2.6
Classifier: Programming Language :: Python :: 2.7
Classifier: Intended Audience :: Developers
Classifier: License :: OSI Approved :: BSD License
Classifier: Operating System :: POSIX
Classifier: Topic :: Text Editors
